threeflex/__init__.py
threeflex-0.1.1.dist-info/DESCRIPTION.rst
threeflex-0.1.1.dist-info/entry_points.txt
threeflex-0.1.1.dist-info/METADATA
threeflex-0.1.1.dist-info/metadata.json
threeflex-0.1.1.dist-info/RECORD
threeflex-0.1.1.dist-info/top_level.txt
threeflex-0.1.1.dist-info/WHEEL
