Metadata-Version: 2.0
Name: threeflex
Version: 0.1.1
Summary: Python driver for Micromeritics 3Flex surface characterization analyzers.
Home-page: http://github.com/numat/threeflex/
Author: Patrick Fuller
Author-email: pat@numat-tech.com
License: GPLv2
Platform: UNKNOWN
Classifier: License :: OSI Approved :: GNU General Public License v2 (GPLv2)
Classifier: Development Status :: 4 - Beta
Classifier: Natural Language :: English
Classifier: Programming Language :: Python
Classifier: Programming Language :: Python :: 2
Classifier: Programming Language :: Python :: 3
Classifier: Programming Language :: Python :: 2.7
Classifier: Programming Language :: Python :: 3.4
Classifier: Topic :: Scientific/Engineering :: Human Machine Interfaces
Classifier: Topic :: Scientific/Engineering :: Electronic Design Automation (EDA)
